proto_logger/__init__.py
proto_logger/__version__.py
proto_logger/core.py
proto_logger-1.0.0.dist-info/METADATA
proto_logger-1.0.0.dist-info/RECORD
proto_logger-1.0.0.dist-info/WHEEL
proto_logger-1.0.0.dist-info/top_level.txt
