Metadata-Version: 2.1
Name: proto-logger
Version: 1.0.0
Summary: proto_logger package.
Home-page: https://github.com/xing-xiao/ProtoPackage/proto_logger
Author: Xiao Xing
Author-email: lo0o.xing@gmail.com
License: MIT
Platform: UNKNOWN
Classifier: License :: OSI Approved :: MIT License
Classifier: Programming Language :: Python
Classifier: Programming Language :: Python :: 3
Classifier: Programming Language :: Python :: 3.6
Classifier: Programming Language :: Python :: Implementation :: CPython
Classifier: Programming Language :: Python :: Implementation :: PyPy
Requires-Python: >=3.6.0
